pyfk/__init__.py
pyfk/setting.py
pyfk/config/__init__.py
pyfk/config/config.py
pyfk/config/radiats.py
pyfk/gf/__init__.py
pyfk/gf/gf.py
pyfk/gf/waveform_integration.cpython-36m-darwin.so
pyfk/sync/__init__.py
pyfk/sync/sync.py
pyfk/taup/__init__.py
pyfk/taup/taup.cpython-36m-darwin.so
pyfk/tests/__init__.py
pyfk/tests/config/__init__.py
pyfk/tests/config/test_config.py
pyfk/tests/data/1066a.nd
pyfk/tests/data/ak135f_no_mud.nd
pyfk/tests/data/hk
pyfk/tests/data/prem.nd
pyfk/tests/data/hk_gf/10.grn.0
pyfk/tests/data/hk_gf/10.grn.1
pyfk/tests/data/hk_gf/10.grn.2
pyfk/tests/data/hk_gf/10.grn.3
pyfk/tests/data/hk_gf/10.grn.4
pyfk/tests/data/hk_gf/10.grn.5
pyfk/tests/data/hk_gf/10.grn.6
pyfk/tests/data/hk_gf/10.grn.7
pyfk/tests/data/hk_gf/10.grn.8
pyfk/tests/data/hk_gf/20.grn.0
pyfk/tests/data/hk_gf/20.grn.1
pyfk/tests/data/hk_gf/20.grn.2
pyfk/tests/data/hk_gf/20.grn.3
pyfk/tests/data/hk_gf/20.grn.4
pyfk/tests/data/hk_gf/20.grn.5
pyfk/tests/data/hk_gf/20.grn.6
pyfk/tests/data/hk_gf/20.grn.7
pyfk/tests/data/hk_gf/20.grn.8
pyfk/tests/data/hk_gf/30.grn.0
pyfk/tests/data/hk_gf/30.grn.1
pyfk/tests/data/hk_gf/30.grn.2
pyfk/tests/data/hk_gf/30.grn.3
pyfk/tests/data/hk_gf/30.grn.4
pyfk/tests/data/hk_gf/30.grn.5
pyfk/tests/data/hk_gf/30.grn.6
pyfk/tests/data/hk_gf/30.grn.7
pyfk/tests/data/hk_gf/30.grn.8
pyfk/tests/data/sync_filter/50.grn.0
pyfk/tests/data/sync_filter/50.grn.1
pyfk/tests/data/sync_filter/50.grn.2
pyfk/tests/data/sync_filter/50.grn.3
pyfk/tests/data/sync_filter/50.grn.4
pyfk/tests/data/sync_filter/50.grn.5
pyfk/tests/data/sync_filter/50.grn.6
pyfk/tests/data/sync_filter/50.grn.7
pyfk/tests/data/sync_filter/50.grn.8
pyfk/tests/data/sync_prem_ep/50.grn.a
pyfk/tests/data/sync_prem_ep/50.grn.b
pyfk/tests/data/sync_prem_ep/50.grn.c
pyfk/tests/data/sync_prem_gcmt/prem.r
pyfk/tests/data/sync_prem_gcmt/prem.t
pyfk/tests/data/sync_prem_gcmt/prem.z
pyfk/tests/data/sync_prem_gcmt/test_gcmt
pyfk/tests/data/sync_prem_sf/50.grn.0
pyfk/tests/data/sync_prem_sf/50.grn.1
pyfk-0.1.0a1.dist-info/LICENSE
pyfk-0.1.0a1.dist-info/METADATA
pyfk-0.1.0a1.dist-info/WHEEL
pyfk-0.1.0a1.dist-info/top_level.txt
pyfk-0.1.0a1.dist-info/RECORD
