Metadata-Version: 2.1
Name: pyfk
Version: 0.1.0a1
Summary: Pyfk is the python version of FK used to calculate the Green's function and the synthetic waveforms for the 1D Earth model.
Home-page: https://github.com/ziyixi/pyfk
Author: Ziyi Xi
Author-email: xiziyi2015@gmail.com
License: MIT
Platform: OS Independent
Classifier: Development Status :: 3 - Alpha
Classifier: Environment :: Console
Classifier: Intended Audience :: Science/Research
Classifier: Intended Audience :: Developers
Classifier: License :: OSI Approved :: MIT License
Classifier: Operating System :: OS Independent
Classifier: Programming Language :: Python
Classifier: Programming Language :: Python :: 3
Classifier: Programming Language :: Python :: 3.6
Classifier: Programming Language :: Python :: 3.7
Classifier: Programming Language :: Python :: 3.8
Classifier: Topic :: Scientific/Engineering
Classifier: Topic :: Scientific/Engineering :: Physics
Requires-Python: >=3.6
Requires-Dist: numpy
Requires-Dist: obspy
Requires-Dist: cython
Requires-Dist: scipy
Requires-Dist: cysignals
